classify.py
lineages.py
version.py
moose_classifier-0.15.dist-info/METADATA
moose_classifier-0.15.dist-info/WHEEL
moose_classifier-0.15.dist-info/entry_points.txt
moose_classifier-0.15.dist-info/top_level.txt
moose_classifier-0.15.dist-info/RECORD
