Metadata-Version: 2.4
Name: moose_classifier
Version: 0.15
Summary: Alignment based taxonomic classifier
Author: Chris Rosenthal
Author-email: crosenth@gmail.com
Maintainer-email: Dan Hoogestraat <dhoogest@uw.edu>
License-Expression: GPL-3.0-only
Project-URL: repository, https://github.com/crosenth/moose
Keywords: bioinformatics,blast,classifier,dna,genetics,genomics,ncbi,rna
Classifier: Environment :: Console
Classifier: Intended Audience :: End Users/Desktop
Classifier: Operating System :: OS Independent
Classifier: Programming Language :: Python :: 3
Requires-Python: >=3.7
Requires-Dist: pandas>=2.0.2
